rtl/alu32.v
//==================================================
// 32-bit ALU
// Supported Operations:
// ADD, SUB, AND, OR, XOR, NOT,
// Shift Left, Shift Right, Compare
//==================================================

module alu32 (
    input [31:0] A,
    input [31:0] B,
    input [3:0] opcode,
    output reg [31:0]result // golden rule: for reg # always will use it 
);
    always@(*)
    begin
        case (opcode)
       
             4'b0000:result=A+B;
             4'b0001:result=A-B;
             4'b0010:result=A&B;
             4'b0011:result=A|B;
             4'b0100:result=A^B;
             4'b0101:result=~A;
             4'b0110:result=A<<1;
             4'b0111:result=A>>1;
             4'b1000:result=(A>B)? 32'd1:32'd0;

             default:result=32'd0;

        endcase 
    end
endmodule

tb/alu32_tb.v
`timescale 1ns/1ps

module alu32_tb;
    reg [31:0]A;
    reg [31:0]B;
    reg [3:0]opcode;
    
    wire[31:0]result;

    //Alu instantiation
    alu32 uut(
        .A(A),
        .B(B),
        .opcode(opcode),
        .result(result)
    );
    initial begin
        $monitor(                                       // What happens? Suppose A = 10; Console Time=0 A=10 B=5 Opcode=0000 Result=15
            "Time=%0t A=%d B=%d opcode=%b result=%d",   // No extra $monitor.It keeps watching.
            $time,A,B,opcode,result
        );
    end
    initial begin
        $dumpfile("waveform.vcd");
        $dumpvars(0,alu32_tb);

        A=10;
        B=15;
        opcode=4'b0000;

        #20;

        A=50;
        B=23;
        opcode=4'b0001;

        #20;

        A=29;
        B=25;
        opcode=4'b0010;

       #20;

        A=30;
        B=40;
        opcode=4'b0011;

        #20;

        A=40;
        B=50;
        opcode=4'b0100;

        #20;

        A=35;
        B=55;
        opcode=4'b0101;

        #20;

        A=5;
        opcode=4'b0110;

        #20;

        A=12;
        opcode=4'b0111;

        #20;

        A=60;
        B=40;
        opcode=4'b1000;

        #20;
    $finish;
    end

endmodule

sim/waveform.vcd
$date
	Mon Aug  3 13:27:31 2026
$end
$version
	Icarus Verilog
$end
$timescale
	1ps
$end
$scope module alu32_tb $end
$var wire 32 ! result [31:0] $end
$var reg 32 " A [31:0] $end
$var reg 32 # B [31:0] $end
$var reg 4 $ opcode [3:0] $end
$scope module uut $end
$var wire 32 % A [31:0] $end
$var wire 32 & B [31:0] $end
$var wire 4 ' opcode [3:0] $end
$var reg 32 ( result [31:0] $end
$upscope $end
$upscope $end
$enddefinitions $end
$comment Show the parameter values. $end
$dumpall
$end
#0
$dumpvars
b11001 (
b0 '
b1111 &
b1010 %
b0 $
b1111 #
b1010 "
b11001 !
$end
#20000
b11011 !
b11011 (
b1 $
b1 '
b10111 #
b10111 &
b110010 "
b110010 %
#40000
b11001 !
b11001 (
b10 $
b10 '
b11001 #
b11001 &
b11101 "
b11101 %
#60000
b111110 !
b111110 (
b11 $
b11 '
b101000 #
b101000 &
b11110 "
b11110 %
#80000
b11010 !
b11010 (
b100 $
b100 '
b110010 #
b110010 &
b101000 "
b101000 %
#100000
b11111111111111111111111111011100 !
b11111111111111111111111111011100 (
b101 $
b101 '
b110111 #
b110111 &
b100011 "
b100011 %
#120000
b1010 !
b1010 (
b110 $
b110 '
b101 "
b101 %
#140000
b110 !
b110 (
b111 $
b111 '
b1100 "
b1100 %
#160000
b1 !
b1 (
b1000 $
b1000 '
b101000 #
b101000 &
b111100 "
b111100 %
